market_data_ibkr/__init__.py
market_data_ibkr/errors.py
market_data_ibkr/mapping.py
market_data_ibkr/metrics.py
market_data_ibkr/pacing.py
market_data_ibkr/provider.py
market_data_ibkr/server.py
market_data_ibkr/session.py
market_data_ibkr/settings.py
market_data_ibkr-1.1.7.dist-info/licenses/LICENSE
market_data_ibkr-1.1.7.dist-info/METADATA
market_data_ibkr-1.1.7.dist-info/WHEEL
market_data_ibkr-1.1.7.dist-info/top_level.txt
market_data_ibkr-1.1.7.dist-info/RECORD
