Metadata-Version: 2.4
Name: market-data-ibkr
Version: 1.1.7
Summary: Interactive Brokers provider implementation for market-data-core
Author: OpenBB
License: MIT
Project-URL: Homepage, https://github.com/mjdevaccount/market-data-ibkr
Project-URL: Documentation, https://github.com/mjdevaccount/market-data-ibkr#readme
Project-URL: Repository, https://github.com/mjdevaccount/market-data-ibkr
Project-URL: Issues, https://github.com/mjdevaccount/market-data-ibkr/issues
Project-URL: Changelog, https://github.com/mjdevaccount/market-data-ibkr/releases
Requires-Python: >=3.11
License-File: LICENSE
Requires-Dist: market-data-core<2.0.0,>=1.2.9
Requires-Dist: ib_insync<1.0,>=0.9.86
Requires-Dist: fastapi<0.116,>=0.115
Requires-Dist: uvicorn[standard]<0.33,>=0.32
Requires-Dist: prometheus-client<0.22,>=0.21
Requires-Dist: pydantic<3.0,>=2.7
Requires-Dist: python-dotenv>=1.0
Requires-Dist: loguru<0.8,>=0.7
Provides-Extra: dev
Requires-Dist: pytest>=8.2; extra == "dev"
Requires-Dist: pytest-asyncio>=0.23; extra == "dev"
Requires-Dist: pytest-mock>=3.12; extra == "dev"
Requires-Dist: ruff>=0.6; extra == "dev"
Requires-Dist: mypy>=1.11; extra == "dev"
Dynamic: license-file
